LICENSE.txt
MANIFEST.in
README.txt
setup.cfg
setup.py
Oort.egg-info/PKG-INFO
Oort.egg-info/SOURCES.txt
Oort.egg-info/dependency_links.txt
Oort.egg-info/not-zip-safe
Oort.egg-info/requires.txt
Oort.egg-info/top_level.txt
oort/__init__.py
oort/rdfview.py
oort/test/__init__.py
oort/test/helper.py
oort/test/test_misc.py
oort/test/test_rdfview.py
oort/test/test_rdfview_context.py
oort/test/testdata.n3
oort/test/util/test_fodder.py
oort/util/__init__.py
oort/util/_genshifilters.py
oort/util/code.py
oort/util/graphs.py
oort/util/queries.py
