Metadata-Version: 1.0
Name: Oort
Version: 0.4
Summary: A toolkit for accessing RDF graphs as plain objects.
Home-page: http://oort.to/
Author: Niklas Lindström
Author-email: lindstream@gmail.com
License: BSD
Keywords: rdf graph toolkit database orm programming
Platform: any
Classifier: Development Status :: 4 - Beta
Classifier: Intended Audience :: Developers
Classifier: Intended Audience :: Information Technology
Classifier: License :: OSI Approved :: BSD License
Classifier: Operating System :: OS Independent
Classifier: Programming Language :: Python
Classifier: Topic :: Software Development :: Libraries
Classifier: Topic :: Software Development :: Libraries :: Python Modules
